dictionary_transformer/__init__.py
dictionary_transformer/exceptions.py
dictionary_transformer/transformer.py
dictionary_transformer-0.0.3.dist-info/METADATA
dictionary_transformer-0.0.3.dist-info/WHEEL
dictionary_transformer-0.0.3.dist-info/top_level.txt
dictionary_transformer-0.0.3.dist-info/RECORD
