Metadata-Version: 2.1
Name: dictionary-transformer
Version: 0.0.3
Summary: Dictionary Transformer
Home-page: https://github.com/rimvydaszilinskas/py-json-transformer
Author: Rimvydas Zilinskas
Author-email: rimvydas.zilinskas@yahoo.com
License: MIT
